Metadata-Version: 2.1
Name: cs200
Version: 2.4.5
Summary: A SIMPLE package for simplifying concepts available on wikipedia.
Home-page: https://github.com/dev-segal/cs200
Author: Joshua Segal
Author-email: gitpulljoshuasegal@gmail.com
License: UNKNOWN
Platform: UNKNOWN
Classifier: Programming Language :: Python :: 3
Classifier: Operating System :: OS Independent
